tgzr/shell_apps/manager_panel/__init__.py
tgzr/shell_apps/manager_panel/_version.py
tgzr/shell_apps/manager_panel/app.py
tgzr/shell_apps/manager_panel/run_dev.py
tgzr/shell_apps/manager_panel/run_native.py
tgzr/shell_apps/manager_panel/components/__init__.py
tgzr/shell_apps/manager_panel/components/apps_tab.py
tgzr/shell_apps/manager_panel/components/plugins_tab.py
tgzr/shell_apps/manager_panel/components/settings.py
tgzr/shell_apps/manager_panel/components/settings_tab.py
tgzr/shell_apps/manager_panel/components/state.py
tgzr/shell_apps/manager_panel/pages/__init__.py
tgzr_shell_apps_manager_panel-0.100.dist-info/METADATA
tgzr_shell_apps_manager_panel-0.100.dist-info/WHEEL
tgzr_shell_apps_manager_panel-0.100.dist-info/entry_points.txt
tgzr_shell_apps_manager_panel-0.100.dist-info/licenses/LICENSE
tgzr_shell_apps_manager_panel-0.100.dist-info/RECORD
