Metadata-Version: 2.4
Name: tgzr.shell_apps.manager_panel
Version: 0.100
Summary: Desktop GUI to manage TGZR installaions and their configuration.
Project-URL: Documentation, https://github.com/open-tgzr/tgzr.shell_apps.manager_panel#readme
Project-URL: Issues, https://github.com/open-tgzr/tgzr.shell_apps.manager_panel/issues
Project-URL: Source, https://github.com/open-tgzr/tgzr.shell_apps.manager_panel
Author-email: Dee <dee.sometech@gmail.com>
License-Expression: GPL-3.0-or-later
License-File: LICENSE
Classifier: Development Status :: 4 - Beta
Classifier: Programming Language :: Python
Classifier: Programming Language :: Python :: 3.12
Classifier: Programming Language :: Python :: 3.13
Classifier: Programming Language :: Python :: 3.14
Classifier: Programming Language :: Python :: Implementation :: CPython
Classifier: Programming Language :: Python :: Implementation :: PyPy
Requires-Python: >=3.9
Requires-Dist: nicegui>=2.24.2
Requires-Dist: pywebview[qt]>=6.1
Requires-Dist: tgzr-cli>=0.100
Requires-Dist: tgzr-contextual-settings>=0.100
Requires-Dist: tgzr-nice>=0.100
Requires-Dist: tgzr-package-management>=0.100
Requires-Dist: tgzr-shell>=0.100
